LICENSE
README.md
setup.py
coinstac_computation/__init__.py
coinstac_computation/nodes.py
coinstac_computation/utils.py
coinstac_computation.egg-info/PKG-INFO
coinstac_computation.egg-info/SOURCES.txt
coinstac_computation.egg-info/dependency_links.txt
coinstac_computation.egg-info/requires.txt
coinstac_computation.egg-info/top_level.txt