Metadata-Version: 2.1
Name: coinstac-computation
Version: 0.66
Summary: Generic computation implementation on COINSTAC.
Home-page: https://github.com/trendscenter/coinstac-computation
Author: Aashis Khana1
Author-email: sraashis@gmail.com
License: MIT
Platform: UNKNOWN
Classifier: License :: OSI Approved :: MIT License
Classifier: Programming Language :: Python :: 3.6
Classifier: Programming Language :: Python :: 3.7
License-File: LICENSE
